py3_email.py
pyemail.py
pymail.py
python_email.py
py3_email-1.0.dist-info/LICENSE
py3_email-1.0.dist-info/METADATA
py3_email-1.0.dist-info/WHEEL
py3_email-1.0.dist-info/top_level.txt
py3_email-1.0.dist-info/RECORD
